nfoursid/__init__.py
nfoursid/kalman.py
nfoursid/nfoursid.py
nfoursid/state_space.py
nfoursid/utils.py
nfoursid/tests/__init__.py
nfoursid/tests/test_kalman.py
nfoursid/tests/test_nfoursid.py
nfoursid/tests/test_state_space.py
nfoursid/tests/test_utils.py
nfoursid-1.0.1.dist-info/LICENSE
nfoursid-1.0.1.dist-info/METADATA
nfoursid-1.0.1.dist-info/WHEEL
nfoursid-1.0.1.dist-info/top_level.txt
nfoursid-1.0.1.dist-info/RECORD
