Metadata-Version: 2.1
Name: nfoursid
Version: 1.0.1
Summary: Implementation of N4SID, Kalman filtering and state-space models
Home-page: https://github.com/spmvg/nfoursid
Author: Steven van Gemert
Author-email: steven@vangemert.dev
License: MIT
Classifier: Development Status :: 5 - Production/Stable
Classifier: License :: OSI Approved :: MIT License
Classifier: Programming Language :: Python :: 3
Requires-Python: >=3.7
License-File: LICENSE
Requires-Dist: matplotlib (>=3.3)
Requires-Dist: numpy (>=1.19)
Requires-Dist: pandas (>=1.1)
